yapywrangler/__init__.py
yapywrangler/yapywrangler.py
yapywrangler-1.2.dist-info/LICENSE
yapywrangler-1.2.dist-info/METADATA
yapywrangler-1.2.dist-info/WHEEL
yapywrangler-1.2.dist-info/top_level.txt
yapywrangler-1.2.dist-info/RECORD
